mixin_templatetag/__init__.py
mixin_templatetag/componentnodes.py
mixin_templatetag/mixinnodes.py
mixin_templatetag/templatetags/__init__.py
mixin_templatetag/templatetags/mixins.py
django_template_mixins-0.3.1.dist-info/LICENSE
django_template_mixins-0.3.1.dist-info/METADATA
django_template_mixins-0.3.1.dist-info/WHEEL
django_template_mixins-0.3.1.dist-info/top_level.txt
django_template_mixins-0.3.1.dist-info/RECORD
