Metadata-Version: 2.1
Name: django-template-mixins
Version: 0.3.1
Summary: Contains template tags for mixins (in this case, local-template repeatable functions) and components (a separate file that has slots that can be replaced).
Home-page: https://github.com/benlei/django-template-mixins
Author: Benjamin Lei
License: BSD
Project-URL: Source, https://github.com/benlei/django-template-mixins
Keywords: django template templatetag mixin component slot
Platform: UNKNOWN
Classifier: Environment :: Web Environment
Classifier: Framework :: Django
Classifier: Framework :: Django :: 2.0
Classifier: Framework :: Django :: 2.1
Classifier: Framework :: Django :: 2.2
Classifier: Framework :: Django :: 3.0
Classifier: Intended Audience :: Developers
Classifier: License :: OSI Approved :: BSD License
Classifier: Operating System :: OS Independent
Classifier: Programming Language :: Python :: 3
Classifier: Programming Language :: Python :: 3.5
Classifier: Programming Language :: Python :: 3.6
Classifier: Programming Language :: Python :: 3.7
Classifier: Programming Language :: Python :: 3.8
Classifier: Programming Language :: Python :: 3 :: Only
Classifier: Topic :: Utilities
Requires-Dist: django
